{
"meta":{"test_sets":[],"test_metrics":[],"learn_metrics":[{"best_value":"Min","name":"Logloss"}],"launch_mode":"Train","parameters":"","iteration_count":152,"learn_sets":["learn"],"name":"experiment"},
"iterations":[
{"learn":[0.692652993],"iteration":0,"passed_time":0.05930698779,"remaining_time":8.955355156},
{"learn":[0.691808989],"iteration":1,"passed_time":0.06118977908,"remaining_time":4.589233431,,
{"learn":[0.691118422],"iteration":2,"passed_time":0.1862570909,"remaining_time":9.250768847},
{"learn":[0.6905929583],"iteration":3,"passed_time":0.2233270115,"remaining_time":8.263099426},
{"learn":[0.6912850664],"iteration":4,"passed_time":0.4894817968,"remaining_time":8.810672343},
{"learn":[0.6908852429],"iteration":5,"passed_time":0.5535183841,"remaining_time":8.210522697},
{"learn":[0.690417418],"iteration":6,"passed_time":0.6204243481,"remaining_time":7.799620376},
{"learn":[0.6900264899],"iteration":7,"passed_time":0.635673631,"remaining_time":6.912950737},
{"learn":[0.6895980277],"iteration":8,"passed_time":0.6755852734,"remaining_time":6.455592612},
{"learn":[0.6893310625],"iteration":9,"passed_time":0.7445910416,"remaining_time":6.329023853},
{"learn":[0.6890130016],"iteration":10,"passed_time":0.8854432998,"remaining_time":6.761567017},
{"learn":[0.6887273279],"iteration":11,"passed_time":1.041704816,"remaining_time":7.205124974},
{"learn":[0.6885502509],"iteration":12,"passed_time":1.049970419,"remaining_time":6.622890337},
{"learn":[0.6882454035],"iteration":13,"passed_time":1.151133938,"remaining_time":6.660132071},
{"learn":[0.6879976466],"iteration":14,"passed_time":1.222091723,"remaining_time":6.517822523},
{"learn":[0.6876320478],"iteration":15,"passed_time":1.255227797,"remaining_time":6.197687247},
{"learn":[0.6873046454],"iteration":16,"passed_time":1.347109318,"remaining_time":6.18085452},
{"learn":[0.6871059468],"iteration":17,"passed_time":1.410724809,"remaining_time":6.034767237},
{"learn":[0.6868179153],"iteration":18,"passed_time":1.52012561,"remaining_time":6.080502438},
{"learn":[0.686501444],"iteration":19,"passed_time":1.572286411,"remaining_time":5.896074042},
{"learn":[0.6861837999],"iteration":20,"passed_time":1.682188199,"remaining_time":5.927710795},
{"learn":[0.6859803457],"iteration":21,"passed_time":1.688328292,"remaining_time":5.602180242},
{"learn":[0.6857105374],"iteration":22,"passed_time":1.715018931,"remaining_time":5.368754914},
{"learn":[0.6855130018],"iteration":23,"passed_time":1.780180414,"remaining_time":5.266367058},
{"learn":[0.6853373858],"iteration":24,"passed_time":1.828929292,"remaining_time":5.121002019},
{"learn":[0.685140294],"iteration":25,"passed_time":1.956824477,"remaining_time":5.193111113},
{"learn":[0.6848436297],"iteration":26,"passed_time":2.136342594,"remaining_time":5.380418384},
{"learn":[0.6845800775],"iteration":27,"passed_time":2.224691237,"remaining_time":5.323368317},
{"learn":[0.6842825434],"iteration":28,"passed_time":2.243824468,"remaining_time":5.106634995},
{"learn":[0.6840899948],"iteration":29,"passed_time":2.33496183,"remaining_time":5.059083965},
{"learn":[0.6838778592],"iteration":30,"passed_time":2.431774113,"remaining_time":5.020436878},
{"learn":[0.6836453552],"iteration":31,"passed_time":2.480378766,"remaining_time":4.883245695},
{"learn":[0.6833684271],"iteration":32,"passed_time":2.486114359,"remaining_time":4.670881522},
{"learn":[0.6831656001],"iteration":33,"passed_time":2.535223823,"remaining_time":4.5484898},
{"learn":[0.682985022],"iteration":34,"passed_time":2.588757456,"remaining_time":4.437869924},
{"learn":[0.6827714482],"iteration":35,"passed_time":2.627211624,"remaining_time":4.305707939},
{"learn":[0.6826573794],"iteration":36,"passed_time":2.642402232,"remaining_time":4.142144039},
{"learn":[0.6824639177],"iteration":37,"passed_time":2.65648245,"remaining_time":3.984723675},
{"learn":[0.6822391556],"iteration":38,"passed_time":2.671412419,"remaining_time":3.835874242},
{"learn":[0.6820155407],"iteration":39,"passed_time":2.695553833,"remaining_time":3.70638652},
{"learn":[0.6818984311],"iteration":40,"passed_time":2.72234739,"remaining_time":3.585530709},
{"learn":[0.6817606083],"iteration":41,"passed_time":2.754488799,"remaining_time":3.475902533},
{"learn":[0.6816626464],"iteration":42,"passed_time":2.772808925,"remaining_time":3.353164281},
{"learn":[0.681538826],"iteration":43,"passed_time":2.793983249,"remaining_time":3.238480584},
{"learn":[0.6813661452],"iteration":44,"passed_time":2.854334684,"remaining_time":3.171482982},
{"learn":[0.6812659082],"iteration":45,"passed_time":2.910165742,"remaining_time":3.09995916},
{"learn":[0.6811137901],"iteration":46,"passed_time":2.977296261,"remaining_time":3.04064299},
{"learn":[0.6809760585],"iteration":47,"passed_time":3.036276342,"remaining_time":2.973020584},
{"learn":[0.6807880507],"iteration":48,"passed_time":3.0495085,"remaining_time":2.862803898},
{"learn":[0.6806700305],"iteration":49,"passed_time":3.074199715,"remaining_time":2.766779744},
{"learn":[0.6804800227],"iteration":50,"passed_time":3.102253931,"remaining_time":2.676454371},,
{"learn":[0.6761746627],"iteration":51,"passed_time":7.155240404,"remaining_time":13.76007,
{,
{"learn":[0.6759575288],"iteration":52,"passed_time":7.198739815,"remaining_time":13.44670267},
{"learn":[0.6757355748],"iteration":53,"passed_time":7.221447605,"remaining_time":13.1055901},
{"learn":[0.6754682294],"iteration":54,"passed_time":7.244176737,"remaining_time":12.77609352},
{"learn":[0.6751882038],"iteration":55,"passed_time":7.305225787,"remaining_time":12.52324421},
{"learn":[0.6749768055],"iteration":56,"passed_time":7.358375713,"remaining_time":12.26395952},
{"learn":[0.6747894953],"iteration":57,"passed_time":7.487801049,"remaining_time":12.1354017},
{"learn":[0.6745159156],"iteration":58,"passed_time":7.514902611,"remaining_time":11.84552445},
{"learn":[0.6742446829],"iteration":59,"passed_time":7.536195017,"remaining_time":11.55549903},
{"learn":[0.6740364075],"iteration":60,"passed_time":7.553484249,"remaining_time":11.26831257},
{"learn":[0.6737448745],"iteration":61,"passed_time":7.57376683,"remaining_time":10.99417766},
{"learn":[0.6735238505],"iteration":62,"passed_time":7.594823013,"remaining_time":10.72919442},
{"learn":[0.6733188887],"iteration":63,"passed_time":7.617698451,"remaining_time":10.47433537},
{"learn":[0.6731876625],"iteration":64,"passed_time":7.641437837,"remaining_time":10.22777064},
{"learn":[0.6729372777],"iteration":65,"passed_time":7.768140119,"remaining_time":10.12212197},
{"learn":[0.6727002225],"iteration":66,"passed_time":7.869403132,"remaining_time":9.983571138},
{"learn":[0.6725609005],"iteration":67,"passed_time":7.889417921,"remaining_time":9.745751549},
{"learn":[0.6723948726],"iteration":68,"passed_time":7.910785506,"remaining_time":9.51587242},
{"learn":[0.6722183822],"iteration":69,"passed_time":7.933019452,"remaining_time":9.292965644},
{"learn":[0.6720602815],"iteration":70,"passed_time":7.958784745,"remaining_time":9.079740343},
{"learn":[0.6718652569],"iteration":71,"passed_time":7.979653957,"remaining_time":8.866282174},
{"learn":[0.6716653203],"iteration":72,"passed_time":7.998862345,"remaining_time":8.656303086},
{"learn":[0.6715482651],"iteration":73,"passed_time":8.018945514,"remaining_time":8.452402028},
{"learn":[0.6713931638],"iteration":74,"passed_time":8.071231585,"remaining_time":8.286464427},
{"learn":[0.6711981929],"iteration":75,"passed_time":8.19597495,"remaining_time":8.19597495},
{"learn":[0.6710522537],"iteration":76,"passed_time":8.214865654,"remaining_time":8.00149252},
{"learn":[0.670854706],"iteration":77,"passed_time":8.232527894,"remaining_time":7.810346977},
{"learn":[0.6707364644],"iteration":78,"passed_time":8.250061335,"remaining_time":7.623474398},
{"learn":[0.6705984562],"iteration":79,"passed_time":8.265638626,"remaining_time":7.439074763},
{"learn":[0.6703378803],"iteration":80,"passed_time":8.282119879,"remaining_time":7.259635943},
{"learn":[0.6700573934],"iteration":81,"passed_time":8.298030757,"remaining_time":7.083684792},
{"learn":[0.6698942087],"iteration":82,"passed_time":8.313898412,"remaining_time":6.911554102},
{"learn":[0.6697644577],"iteration":83,"passed_time":8.329954909,"remaining_time":6.743296831},
{"learn":[0.669547292],"iteration":84,"passed_time":8.348932763,"remaining_time":6.580923472},
{"learn":[0.6693173803],"iteration":85,"passed_time":8.40809758,"remaining_time":6.45272605},
{"learn":[0.6691296128],"iteration":86,"passed_time":8.533841031,"remaining_time":6.375858242},
{"learn":[0.6688976639],"iteration":87,"passed_time":8.584733343,"remaining_time":6.243442431},
{"learn":[0.6687711572],"iteration":88,"passed_time":8.602767241,"remaining_time":6.089599283},
{"learn":[0.6685326201],"iteration":89,"passed_time":8.618870498,"remaining_time":5.937444121},
{"learn":[0.6682913596],"iteration":90,"passed_time":8.638133385,"remaining_time":5.790397104},
{"learn":[0.6679748444],"iteration":91,"passed_time":8.654281574,"remaining_time":5.644096679},
{"learn":[0.6678773745],"iteration":92,"passed_time":8.669515724,"remaining_time":5.500015352},
{"learn":[0.6675446412],"iteration":93,"passed_time":8.68574599,"remaining_time":5.359290079},
{"learn":[0.667333234],"iteration":94,"passed_time":8.705198782,"remaining_time":5.223119269},
{"learn":[0.6670615521],"iteration":95,"passed_time":8.721494707,"remaining_time":5.087538579},
{"learn":[0.6669598582],"iteration":96,"passed_time":8.742227331,"remaining_time":4.956933023},
{"learn":[0.6667877147],"iteration":97,"passed_time":8.866202157,"remaining_time":4.885458331},
{"learn":[0.6666373831],"iteration":98,"passed_time":8.950468933,"remaining_time":4.791665186},
{"learn":[0.6664568796],"iteration":99,"passed_time":8.965733457,"remaining_time":4.662181398},
{"learn":[0.6662741639],"iteration":100,"passed_time":8.981582931,"remaining_time":4.535254748},
{"learn":[0.6661396312],"iteration":101,"passed_time":8.998753264,"remaining_time":4.411153561},
{"learn":[0.6659346986],"iteration":102,"passed_time":9.016834625,"remaining_time":4.289562103},
{"learn":[0.665733541],"iteration":103,"passed_time":9.036749606,"remaining_time":4.17080751},
{"learn":[0.6656573111],"iteration":104,"passed_time":9.052948973,"remaining_time":4.052272398},
{"learn":[0.6654759177],"iteration":105,"passed_time":9.069619451,"remaining_time":3.935872592},
{"learn":[0.6653404899],"iteration":106,"passed_time":9.089491935,"remaining_time":3.822683524},
{"learn":[0.6652196563],"iteration":107,"passed_time":9.107241448,"remaining_time":3.710357627},
{"learn":[0.6650453512],"iteration":108,"passed_time":9.165849839,"remaining_time":3.615885716},
{"learn":[0.6648937811],"iteration":109,"passed_time":9.284490922,"remaining_time":3.544987443},
{"learn":[0.664670833],"iteration":110,"passed_time":9.306805995,"remaining_time":3.437649061},
{"learn":[0.6645916338],"iteration":111,"passed_time":9.327313729,"remaining_time":3.331183475},
{"learn":[0.6644370653],"iteration":112,"passed_time":9.347073335,"remaining_time":3.225981062},
{"learn":[0.6642116715],"iteration":113,"passed_time":9.366810671,"remaining_time":3.122270224},
{"learn":[0.6640258644],"iteration":114,"passed_time":9.387929103,"remaining_time":3.020464146},
{"learn":[0.6638781904],"iteration":115,"passed_time":9.408551977,"remaining_time":2.919895441},
{"learn":[0.6637439279],"iteration":116,"passed_time":9.429575746,"remaining_time":2.820813257},
{"learn":[0.6634836372],"iteration":117,"passed_time":9.449938594,"remaining_time":2.722863663},
{"learn":[0.6633674437],"iteration":118,"passed_time":9.4695143,"remaining_time":2.625999764},
{"learn":[0.6632367813],"iteration":119,"passed_time":9.523011011,"remaining_time":2.539469603},
{"learn":[0.6631211704],"iteration":120,"passed_time":9.650500714,"remaining_time":2.472442332},
{"learn":[0.6629596729],"iteration":121,"passed_time":9.676318766,"remaining_time":2.379422647},
{"learn":[0.662800078],"iteration":122,"passed_time":9.690236442,"remaining_time":2.284689893},
{"learn":[0.6625806824],"iteration":123,"passed_time":9.703204615,"remaining_time":2.191046203},
{"learn":[0.6624492749],"iteration":124,"passed_time":9.715922655,"remaining_time":2.098639293},
{"learn":[0.6622460354],"iteration":125,"passed_time":9.728738641,"remaining_time":2.007517497},
{"learn":[0.6621669821],"iteration":126,"passed_time":9.742218606,"remaining_time":1.917759568},
{"learn":[0.6620006362],"iteration":127,"passed_time":9.755319887,"remaining_time":1.829122479},
{"learn":[0.6618281811],"iteration":128,"passed_time":9.769191163,"remaining_time":1.741793773},
{"learn":[0.6617370854],"iteration":129,"passed_time":9.781785032,"remaining_time":1.655379005},
{"learn":[0.6615329545],"iteration":130,"passed_time":9.794632921,"remaining_time":1.570131995},
{"learn":[0.6614043817],"iteration":131,"passed_time":9.808706812,"remaining_time":1.486167699},
{"learn":[0.6611849871],"iteration":132,"passed_time":9.821820158,"remaining_time":1.403117165},
{"learn":[0.6611152883],"iteration":133,"passed_time":9.835589443,"remaining_time":1.321198582},
{"learn":[0.6610576159],"iteration":134,"passed_time":9.886773225,"remaining_time":1.245001073},
{"learn":[0.6609250786],"iteration":135,"passed_time":9.996335211,"remaining_time":1.176039437},
{"learn":[0.6608609572],"iteration":136,"passed_time":10.02251876,"remaining_time":1.097356069},
{"learn":[0.6606794892],"iteration":137,"passed_time":10.0351362,"remaining_time":1.018057296},
{"learn":[0.6605309092],"iteration":138,"passed_time":10.04761177,"remaining_time":0.9397046977},
{"learn":[0.6603129708],"iteration":139,"passed_time":10.06110541,"remaining_time":0.862380464},
{"learn":[0.6601851884],"iteration":140,"passed_time":10.07444007,"remaining_time":0.7859492254},
{"learn":[0.6599551743],"iteration":141,"passed_time":10.08699643,"remaining_time":0.7103518613},
{"learn":[0.6598632801],"iteration":142,"passed_time":10.10049512,"remaining_time":0.635695497},
{"learn":[0.6597090736],"iteration":143,"passed_time":10.11389167,"remaining_time":0.5618828703},
{"learn":[0.6596363806],"iteration":144,"passed_time":10.1275177,"remaining_time":0.4889146476},
{"learn":[0.6595249468],"iteration":145,"passed_time":10.13861053,"remaining_time":0.4166552272},
{"learn":[0.6593544075],"iteration":146,"passed_time":10.14989295,"remaining_time":0.3452344542},
{"learn":[0.6591649247],"iteration":147,"passed_time":10.16147244,"remaining_time":0.2746343904},
{"learn":[0.6590565705],"iteration":148,"passed_time":10.17325678,"remaining_time":0.2048306734},
{"learn":[0.658838707],"iteration":149,"passed_time":10.18477805,"remaining_time":0.1357970407},
{"learn":[0.6587717388],"iteration":150,"passed_time":10.22855711,"remaining_time":0.06773878883},
{"learn":[0.6586343179],"iteration":151,"passed_time":10.31410937,"remaining_time":0}
]}151,"passed_time":2.831079807,"remaining_time":0.2793828757},
{"learn":[0.6784834232],"iteration":152,"passed_time":2.83310218,"remaining_time":0.259238108},
{"learn":[0.6784629881],"iteration":153,"passed_time":2.8350214,"remaining_time":0.2393199883},
{"learn":[0.6784246969],"iteration":154,"passed_time":2.843561906,"remaining_time":0.2201467282},
{"learn":[0.6783830726],"iteration":155,"passed_time":2.845638413,"remaining_time":0.2006539907},
{"learn":[0.6783602008],"iteration":156,"passed_time":2.849040298,"remaining_time":0.1814675349},
{"learn":[0.6783315813],"iteration":157,"passed_time":2.858559501,"remaining_time":0.1628293387},
{"learn":[0.6783157639],"iteration":158,"passed_time":2.881317948,"remaining_time":0.1449719722},
{"learn":[0.678293414],"iteration":159,"passed_time":2.884241325,"remaining_time":0.1261855579},
{"learn":[0.6782546805],"iteration":160,"passed_time":2.887148588,"remaining_time":0.1075955995},
{"learn":[0.6781798651],"iteration":161,"passed_time":2.8903449,"remaining_time":0.08920817591},
{"learn":[0.6781415556],"iteration":162,"passed_time":2.893289752,"remaining_time":0.0710009755},
{"learn":[0.6781125453],"iteration":163,"passed_time":2.923343754,"remaining_time":0.05347580037},
{"learn":[0.6781019415],"iteration":164,"passed_time":2.927941574,"remaining_time":0.0354902009},
{"learn":[0.6780676166],"iteration":165,"passed_time":2.929546345,"remaining_time":0.01764786955},
{"learn":[0.6780578235],"iteration":166,"passed_time":2.93127254,"remaining_time":0}
]}